authx_lite/__init__.py
authx_lite-0.0.1.dist-info/LICENSE
authx_lite-0.0.1.dist-info/WHEEL
authx_lite-0.0.1.dist-info/METADATA
authx_lite-0.0.1.dist-info/RECORD
